PyAuthGG/Administration.py
PyAuthGG/Application.py
PyAuthGG/Exceptions.py
PyAuthGG/__init__.py
PyAuthGG-1.0.7.dist-info/LICENSE.md
PyAuthGG-1.0.7.dist-info/METADATA
PyAuthGG-1.0.7.dist-info/WHEEL
PyAuthGG-1.0.7.dist-info/top_level.txt
PyAuthGG-1.0.7.dist-info/RECORD
